email_audit/__init__.py
email_audit-0.4.0.dist-info/DESCRIPTION.rst
email_audit-0.4.0.dist-info/METADATA
email_audit-0.4.0.dist-info/RECORD
email_audit-0.4.0.dist-info/WHEEL
email_audit-0.4.0.dist-info/metadata.json
email_audit-0.4.0.dist-info/top_level.txt
