Metadata-Version: 2.0
Name: email-audit
Version: 0.4.0
Summary: audit which email addresses can be collected by bots from your sites.
Home-page: https://github.com/fluquid/email-audit
Author: Johannes Ahlmann
Author-email: johannes@fluquid.com
License: MIT
Keywords: email-audit
Platform: UNKNOWN
Classifier: Development Status :: 2 - Pre-Alpha
Classifier: Intended Audience :: Developers
Classifier: License :: OSI Approved :: MIT License
Classifier: Natural Language :: English
Classifier: Programming Language :: Python :: 2
Classifier: Programming Language :: Python :: 2.7
Classifier: Programming Language :: Python :: 3
Classifier: Programming Language :: Python :: 3.4
Classifier: Programming Language :: Python :: 3.5
Requires-Dist: js2py
Requires-Dist: html-to-etree
Requires-Dist: html-text
Requires-Dist: lxml
Requires-Dist: six
